tuindow/__init__.py
tuindow/__main__.py
tuindow/_backend.py
tuindow/api.py
tuindow/buffers.py
tuindow/cursor.py
tuindow/structs.py
tuindow/validation.py
tuindow/window.py
tuindow/examples/__init__.py
tuindow/examples/simple_editor.py
tuindow-1.0.2.dist-info/LICENSE
tuindow-1.0.2.dist-info/METADATA
tuindow-1.0.2.dist-info/WHEEL
tuindow-1.0.2.dist-info/top_level.txt
tuindow-1.0.2.dist-info/RECORD
