Metadata-Version: 2.1
Name: tuindow
Version: 1.0.2
Summary: A small package for creating TUI applications
Home-page: https://github.com/peffjepin/tuindow
Author: Jeffrey Pepin
License: MIT
Platform: linux
Classifier: Programming Language :: Python :: 3
Classifier: Environment :: Console
Classifier: Environment :: Console :: Curses
Classifier: Topic :: Software Development :: User Interfaces
Provides-Extra: dev
Requires-Dist: pytest ; extra == 'dev'
Requires-Dist: mypy ; extra == 'dev'
